obstools_ipgp/__init__.py
obstools_ipgp/noise_models.py
obstools_ipgp/obstest.py
obstools_ipgp/plotPSDs.py
obstools_ipgp/version.py
obstools_ipgp/_examples/.DS_Store
obstools_ipgp/_examples/example_BBOBS.obstest.yaml
obstools_ipgp/_examples/example_SPOBS.obstest.yaml
obstools_ipgp/_examples/example_stations.obstest.yaml
obstools_ipgp/data/.DS_Store
obstools_ipgp/data/obstest.schema.json
obstools_ipgp-1.1.0.dist-info/LICENSE.txt
obstools_ipgp-1.1.0.dist-info/METADATA
obstools_ipgp-1.1.0.dist-info/WHEEL
obstools_ipgp-1.1.0.dist-info/entry_points.txt
obstools_ipgp-1.1.0.dist-info/top_level.txt
obstools_ipgp-1.1.0.dist-info/RECORD
