Metadata-Version: 2.2
Name: obstools_ipgp
Version: 1.1.0
Summary: Ocean bottom seismometer evaluation/processing routines
Home-page: https://github.com/WayneCrawford/obstools_ipgp
Author: Wayne Crawford
Author-email: crawford@ipgp.fr
Keywords: oceanography,marine,OBS
Classifier: Development Status :: 4 - Beta
Classifier: Environment :: Console
Classifier: Intended Audience :: Science/Research
Classifier: Intended Audience :: Developers
Classifier: License :: OSI Approved :: GNU General Public License v3 (GPLv3)
Classifier: Natural Language :: English
Classifier: Operating System :: OS Independent
Classifier: Programming Language :: Python :: 3.8
Classifier: Topic :: Scientific/Engineering
Classifier: Topic :: Scientific/Engineering :: Physics
Requires-Python: >=3.8
License-File: LICENSE.txt
Requires-Dist: obspy>=1.1
Requires-Dist: pyyaml>5.0
Requires-Dist: jsonschema>=2.6
Requires-Dist: jsonref>=0.2
Requires-Dist: progress>=1.5
Requires-Dist: tiskitpy>=0.4
Dynamic: author
Dynamic: author-email
Dynamic: classifier
Dynamic: description
Dynamic: description-content-type
Dynamic: home-page
Dynamic: keywords
Dynamic: requires-dist
Dynamic: requires-python
Dynamic: summary
